difformer_pytorch/__init__.py
difformer_pytorch/difformer.py
difformer_pytorch-0.0.6.dist-info/LICENSE
difformer_pytorch-0.0.6.dist-info/METADATA
difformer_pytorch-0.0.6.dist-info/WHEEL
difformer_pytorch-0.0.6.dist-info/top_level.txt
difformer_pytorch-0.0.6.dist-info/RECORD
